{
  "full_name": "Sandeep Aggarwal",
  "email": "asandeep.me@gmail.com",
  "github_username": "asandeep",
  "project_name": "PY3 GRPC Cookie",
  "project_short_description": "Cookiecutter template to run Python3 GRPC server.",
  "project_slug": "{{ cookiecutter.project_name.lower().replace(' ', '_').replace('-', '_') }}",
  "cement_app_name": "{{ cookiecutter.project_name.title().replace(' ', '') }}",
  "install_precommit_hooks": "y",
  "pypi_username": "{{ cookiecutter.github_username }}",
  "version": "0.1.0",
  "open_source_license": [
    "MIT license",
    "BSD license",
    "ISC license",
    "Apache Software License 2.0",
    "GNU General Public License v3",
    "Not open source"
  ],
  "database": [
    "PostgreSQL", "MySQL", "SQLite", "NA"
  ]
}
